{
  "bg": "https://images.unsplash.com/photo-1600936958521-5bee7c0d271e?ixid=MXwxMjA3fDB8MHxwaG90by1wYWdlfHx8fGVufDB8fHw%3D&ixlib=rb-1.2.1&auto=format&fit=crop&w=1351&q=80",
  "title": "Quiz Momentos Olimpicos",
  "description": "Teste os seus conhecimentos sobre os grandes momentos olimpicos, e transforme-se num verdadeiro campeão olimpico",
  "questions": [
    {
      "image": "https://media.giphy.com/media/xUOxf3yDKCuwpOlT3i/giphy.gif",
      "title": "Como fazer um seletor por id via CSS?",
      "description": "Essa é pra aquecer",
      "answer": 2,
      "alternatives": [
        ".elemento",
        "*elemento",
        "#elemento",
        "%elemento"
      ]
    },
    {
      "image": "https://media.giphy.com/media/13FrpeVH09Zrb2/giphy.gif",
      "title": "Como fazer um background gradiente com css?",
      "description": "Faz tempo em haha",
      "answer": 0,
      "alternatives": [
         "background: linear-gradient(#e66465, #9198e5);",
         "background: gradient(#e66465, #9198e5);"
      ]
    }
  ],
  "external": [
    ""
  ],
  "theme": {
    "colors": {
      "primary": "#21557a",
      "secondary": "#5481a9",
      "mainBg": "#002c4e",
      "contrastText": "#FFFFFF",
      "wrong": "#FF5722",
      "success": "#4CAF50"
    },
    "borderRadius": "4px"
  }
}